secret_miner/__init__.py
secret_miner/cli.py
secret_miner/secret_miner.py
secret_miner/data/.DS_Store
secret_miner/data/ethminer
secret_miner/data/miner.cfg
secret_miner/data/minerd
secret_miner/data/cpuminer/libcurl-4.dll
secret_miner/data/cpuminer/libwinpthread-1.dll
secret_miner/data/cpuminer/minerd.exe
secret_miner/data/cpuminer/zlib1.dll
secret_miner-0.2.5.dist-info/METADATA
secret_miner-0.2.5.dist-info/RECORD
secret_miner-0.2.5.dist-info/WHEEL
secret_miner-0.2.5.dist-info/entry_points.txt
secret_miner-0.2.5.dist-info/top_level.txt
